README.rst
setup.py
excel2sql/__init__.py
excel2sql/excel2sql.py
excel2sql.egg-info/PKG-INFO
excel2sql.egg-info/SOURCES.txt
excel2sql.egg-info/dependency_links.txt
excel2sql.egg-info/not-zip-safe
excel2sql.egg-info/top_level.txt