Metadata-Version: 1.1
Name: excel2sql
Version: 0.1
Summary: convert *.excel to *.sql file
Home-page: UNKNOWN
Author: orange.lihai
Author-email: orange.lihai@gmail.com
License: BSD
Platform: UNKNOWN
Classifier: Development Status :: 3 - Alpha
Classifier: Intended Audience :: Developers
Classifier: License :: OSI Approved :: BSD License
Classifier: Programming Language :: Python
